{"Validation confusion matrices": [[[1522, 5], [0, 4598]], [[1522, 4], [0, 4598]], [[1519, 8], [0, 4598]], [[1522, 4], [0, 4598]], [[1517, 10], [0, 4598]], [[1521, 5], [0, 4598]]], "_step": 9, "_runtime": 8, "_timestamp": 1603985832, "Validation Median Confusion Matrix": [[1521, 5], [0, 4598]], "Validation confusion_matrix": {"_type": "image-file", "path": "media/images/Validation confusion_matrix_2_6e944ede.png", "sha256": "6e944ede432acb5b3915b90f63723df0222f1b197debc229024184019b76d598", "size": 42769, "format": "png", "width": 1920, "height": 1440}, "Validation performance scores": [0.9978190790260445, 0.998254405977092, 0.996510513617856, 0.998254405977092, 0.9956381292505433, 0.9978180049800989], "Validation global performance score": 0.9973824231381211, "Validation Model Performance: repeats=3 K-folds=2": {"_type": "image-file", "path": "media/images/Validation Model Performance: repeats=3 K-folds=2_5_cdbdcfd5.png", "sha256": "cdbdcfd5c3694f70459c7e65ce327a1edefc05b1c84e5295bb3739ee0196612f", "size": 72839, "format": "png", "width": 1920, "height": 1440}, "Final Trained DF 1: Tree Structure": {"_type": "image-file", "path": "media/images/Final Trained DF 1: Tree Structure_6_b14f9688.png", "sha256": "b14f9688e5232933bf48ef30db0b95f88cde4b116ba0dda0e082767ebdbbfb87", "size": 448960, "format": "png", "width": 2057, "height": 2481}, "Trained confusion matrices on Test set": [[340, 0], [0, 1022]], "Trained performance score on test set": 1.0, "Trained confusion_matrix on Test Set": {"_type": "image-file", "path": "media/images/Trained confusion_matrix on Test Set_9_35d70e26.png", "sha256": "35d70e266842fc8133fda78d642e07700e7e532c895a316eba02cb0db44372ec", "size": 42255, "format": "png", "width": 1920, "height": 1440}}