{"Validation confusion matrices": [[[1515, 12], [0, 4598]], [[1515, 11], [0, 4598]], [[1520, 7], [0, 4598]], [[1517, 9], [0, 4598]], [[1520, 7], [0, 4598]], [[1521, 5], [0, 4598]]], "_step": 10, "_runtime": 8, "_timestamp": 1604063159, "Validation Median Confusion Matrix": [[1518, 8], [0, 4598]], "Validation confusion_matrix": {"_type": "image-file", "path": "media/images/Validation confusion_matrix_2_b2975e24.png", "sha256": "b2975e24758b2bf2d78fe3664fe4a9f1944e38d692001b6a9ba2ef9084ffd370", "size": 43669, "format": "png", "width": 1920, "height": 1440}, "Validation performance scores": [0.9947657377695303, 0.9951995684296878, 0.996946703447645, 0.9960723872721889, 0.996946703447645, 0.9978180049800989], "Validation global performance score": 0.9962915175577992, "Validation Model Performance: repeats=3 K-folds=2": {"_type": "image-file", "path": "media/images/Validation Model Performance: repeats=3 K-folds=2_5_ec6c3399.png", "sha256": "ec6c3399be91ce93fa78db16303e169d09576a3512604ec1a42df03b389b68fc", "size": 73108, "format": "png", "width": 1920, "height": 1440}, "Final Trained DF 1: Tree Structure": {"_type": "image-file", "path": "media/images/Final Trained DF 1: Tree Structure_6_6ca7adeb.png", "sha256": "6ca7adeb560debffacb80a8a4c3f0c35285cc084bea929121a658200b7a6c176", "size": 443649, "format": "png", "width": 2035, "height": 2481}, "Trained confusion matrices on Test set": [[340, 0], [0, 1022]], "Trained performance score on test set": 1.0, "Trained confusion_matrix on Test Set": {"_type": "image-file", "path": "media/images/Trained confusion_matrix on Test Set_9_35d70e26.png", "sha256": "35d70e266842fc8133fda78d642e07700e7e532c895a316eba02cb0db44372ec", "size": 42255, "format": "png", "width": 1920, "height": 1440}, "Tree Split Nodes Table": {"_type": "table-file", "path": "media/table/Tree Split Nodes Table_10_db2ef4ff.table.json", "sha256": "db2ef4ff93844c425c8fdc4d760a0b34624394efc571f83828f5e3511e73a831", "size": 1394, "ncols": 5, "nrows": 21}}